dsatools/__init__.py
dsatools/arma.py
dsatools/decomposition.py
dsatools/delay_fmcw.py
dsatools/distances.py
dsatools/frequency.py
dsatools/phase.py
dsatools/roots.py
dsatools/spectrum.py
dsatools/_base/__init__.py
dsatools/_base/_all.py
dsatools/_base/_arma/__init__.py
dsatools/_base/_arma/_ar_burg.py
dsatools/_base/_arma/_ar_cov_ar_mcov.py
dsatools/_base/_arma/_ar_hoyw.py
dsatools/_base/_arma/_ar_levenson_durbin.py
dsatools/_base/_arma/_ar_ls.py
dsatools/_base/_arma/_ar_minnorm.py
dsatools/_base/_arma/_ar_yule_walker.py
dsatools/_base/_arma/_arma_covar_dubrin_innovation.py
dsatools/_base/_arma/_arma_hannan_rissanen.py
dsatools/_base/_arma/_arma_ipz.py
dsatools/_base/_arma/_arma_pade.py
dsatools/_base/_arma/_arma_prony.py
dsatools/_base/_arma/_arma_shanks.py
dsatools/_base/_arma/_arma_shanks_prony_v2.py
dsatools/_base/_arma/_arma_tools.py
dsatools/_base/_arma/_ma_dubrin.py
dsatools/_base/_arma/_ma_innovations.py
dsatools/_base/_arma/_ma_yule_walker.py
dsatools/_base/_classic_psd/__init__.py
dsatools/_base/_classic_psd/_capone.py
dsatools/_base/_classic_psd/_kernel_periodogram.py
dsatools/_base/_classic_psd/_periodogram.py
dsatools/_base/_classic_psd/_slepian.py
dsatools/_base/_delay_fmcw/__init__.py
dsatools/_base/_delay_fmcw/_full_unwraped_corrphase.py
dsatools/_base/_delay_fmcw/_full_unwraped_phase.py
dsatools/_base/_delay_fmcw/_fullcorrphase.py
dsatools/_base/_delay_fmcw/_fullphase.py
dsatools/_base/_delay_fmcw/_unwraped_phase0.py
dsatools/_base/_distances/__init__.py
dsatools/_base/_distances/_cdf.py
dsatools/_base/_distances/_distances.py
dsatools/_base/_distances/_distances_matrix.py
dsatools/_base/_frequency/__init__.py
dsatools/_base/_frequency/_frequency_cfd.py
dsatools/_base/_frequency/_frequency_fft.py
dsatools/_base/_imf_decomposition/__init__.py
dsatools/_base/_imf_decomposition/_emd.py
dsatools/_base/_imf_decomposition/_ewt.py
dsatools/_base/_imf_decomposition/_hvd.py
dsatools/_base/_imf_decomposition/_vmd.py
dsatools/_base/_phase_init/__init__.py
dsatools-0.1.95.dist-info/LICENSE
dsatools-0.1.95.dist-info/METADATA
dsatools-0.1.95.dist-info/WHEEL
dsatools-0.1.95.dist-info/top_level.txt
dsatools-0.1.95.dist-info/RECORD
