Metadata-Version: 2.1
Name: dsatools
Version: 0.1.95
Summary: The library with a most popular tools for Digital Signal Analysis (DSA)  
Home-page: https://github.com/MVRonkin/dsatools
Author: Mikhail Ronkin
Author-email: mvRonkin@gmail.com
License: MIT
Download-URL: https://github.com/MVRonkin/dsatools/archive/547abfbb9e452703bb83f90c4d66a350ee4e2ae3.zip
Keywords: Digital Signal Analysis,Signal Processing,Digital Signal Processing,Digital Spectrum Processing,Digital Spectrum Analysis
Platform: UNKNOWN
Classifier: License :: OSI Approved :: MIT License
Classifier: Programming Language :: Python :: 3
Classifier: Programming Language :: Python :: 3.6
Classifier: Programming Language :: Python :: 3.7
Requires-Dist: numpy
Requires-Dist: scipy
Requires-Dist: matplotlib
